{
    "input_raw_path":           "/media/rami/18TB/Alpha BTX/Large patches/C01/",
    "input_gt_path":            "/media/rami/18TB/Alpha BTX/Large patches/",
    "input_gt_center_path":     "/media/rami/18TB/Alpha BTX/Large patches/",
    "input_bg_path":            "/media/rami/18TB/Alpha BTX/Large patches/C00/",
    "input_weigth_path":        "",
    "input_model_path":         "/media/10TB/Projects/alpha-btx/segmentation/input/models/",
    "output_model_path":        "/media/10TB/Projects/alpha-btx/segmentation/output/models/",
    "output_prediction_path":   "/media/rami/18TB/Alpha BTX/Prediction/",
    "writer_path":              "/home/rami/runs/",
    "input_model":              "model_1000.dat",
    "output_folder_prefix":     "Alpha-BTX Retraining",
    "model_name":               ""
}
